image_pyqt-0.0.2.0.0.dist-info/DESCRIPTION.rst
image_pyqt-0.0.2.0.0.dist-info/METADATA
image_pyqt-0.0.2.0.0.dist-info/RECORD
image_pyqt-0.0.2.0.0.dist-info/WHEEL
image_pyqt-0.0.2.0.0.dist-info/metadata.json
image_pyqt-0.0.2.0.0.dist-info/top_level.txt
imagepyqt/__init__.py
imagepyqt/myQt.py
imagepyqt/data/Readme.md
imagepyqt/data/__init__.py
imagepyqt/data/installing_imagepyqt.png
imagepyqt/data/test.png
imagepyqt/demos/__init__.py
imagepyqt/demos/__main__.py
imagepyqt/demos/demo.py
imagepyqt/widgets/__init__.py
imagepyqt/widgets/imwidget.py
