Metadata-Version: 2.0
Name: image-pyqt
Version: 0.0.2.0.0
Summary: An Image Widget for display OpenCV Mat image
Home-page: http://www.github.com/ausk/imagepyqt
Author: ausk@github.com
Author-email: jincsu@126.com
License: MIT
Platform: UNKNOWN
Classifier: Programming Language :: Python :: 3
Classifier: Programming Language :: Python :: 3.5
Classifier: Development Status :: 4 - Beta
Classifier: Topic :: Utilities
Classifier: License :: OSI Approved :: MIT License
Requires-Dist: numpy
